[
  {
    "text": "Хотите знать, кто вы? Не спрашивайте. Действуйте! Действие будет описывать и определять вас",
    "author": "Томас Джефферсон"
  },
  {
    "text": "В ту минуту, когда вы соглашаетесь на меньшее по сравнению с тем, что заслуживаете, вы получаете даже меньше, чем то, на что согласились",
    "author": "Морин Дауд"
  },
  {
    "text": "Многое кажется невозможным, пока ты этого не сделаешь",
    "author": "Нельсон Мандела"
  },
  {
    "text": "Каждое утро начинай с чтения списка самых богатых людей. Если тебя там нет – берись за работу",
    "author": "Роберт Орбен"
  },
  {
    "text": "Успешные люди делают то, что неуспешные не хотят делать. Не стремитесь, чтобы было легче, стремитесь, чтобы было лучше",
    "author": "Джим Рон"
  },
  {
    "text": "Чтобы дойти до цели, человеку нужно только одно. Идти",
    "author": "Оноре де Бальзак"
  },
  {
    "text": "Ты никогда не переплывёшь океан, если будешь бояться потерять берег из виду",
    "author": "Христофор Колумб"
  },
  {
    "text": "Желание добиться успеха без упорного труда схоже с желанием снять урожай там, где вы не сажали семена",
    "author": "Дэвид Блай"
  },
  {
    "text": "Не бойтесь пожертвовать хорошим ради еще лучшего",
    "author": "Джон Рокфеллер"
  },
  {
    "text": "Одна победа не ведет к успеху, в отличие от постоянного желания побеждать",
    "author": "Винс Ломбарди"
  }
]
